safegraphql/__init__.py
safegraphql/__version__.py
safegraphql/client.py
safegraphql/error_types.py
safegraphql/trash.py
safegraphql/types.py
safegraphQL-0.5.23.dist-info/LICENSE.txt
safegraphQL-0.5.23.dist-info/METADATA
safegraphQL-0.5.23.dist-info/WHEEL
safegraphQL-0.5.23.dist-info/top_level.txt
safegraphQL-0.5.23.dist-info/RECORD
