Metadata-Version: 2.1
Name: safegraphQL
Version: 0.5.23
Summary: graphQL API of safegraph.com using Python functions
Home-page: https://github.com/echong-SG/API-python-client-MKilic
Author: Renas Mirkan Kilic
Author-email: mirkanbaba1@gmail.com
License: MIT
Keywords: api graphql protocol rest relay gql client safegraph.com safegraph-api
Platform: any
Classifier: Intended Audience :: Science/Research
Classifier: Topic :: Software Development :: Libraries
Classifier: Programming Language :: Python :: 3
Classifier: Programming Language :: Python :: 3.6
Classifier: Programming Language :: Python :: 3.7
Classifier: Programming Language :: Python :: 3.8
Classifier: Programming Language :: Python :: 3.9
Classifier: Programming Language :: Python :: Implementation :: PyPy
Requires-Dist: pandas (==1.3.2)
Requires-Dist: gql (==3.0.0b0)
Requires-Dist: aiohttp (<3.8.0,>=3.7.1)
Requires-Dist: nest-asyncio (==1.5.1)
